LICENSE
MANIFEST.in
README.md
setup.py
grunt/__init__.py
grunt/utils.py
grunt/management/.DS_Store
grunt/management/__init__.py
grunt/management/__init__.pyc
grunt/management/commands/__init__.py
grunt/management/commands/__init__.pyc
grunt/management/commands/gruntinit.py
grunt/management/commands/gruntinit.pyc
grunt/management/commands/gruntserver.py
grunt/management/commands/gruntserver.pyc
grunt/templates/.DS_Store
grunt/templates/grunt/Gruntfile.js
grunt/templates/grunt/package.json
grunt_django.egg-info/PKG-INFO
grunt_django.egg-info/SOURCES.txt
grunt_django.egg-info/dependency_links.txt
grunt_django.egg-info/top_level.txt